draup_django/__init__.py
draup_django/handler.py
draup_django/parser.py
draup_django/utility.py
test/__init__.py
draup_django-1.4.0.dist-info/LICENSE
draup_django-1.4.0.dist-info/METADATA
draup_django-1.4.0.dist-info/WHEEL
draup_django-1.4.0.dist-info/top_level.txt
draup_django-1.4.0.dist-info/RECORD
