Metadata-Version: 2.1
Name: draup-django
Version: 1.4.0
Summary: Django Utility - Draup Labs
Home-page: https://github.com/Draup-Zinnov/draup_django
Author: Arpit | Teja | Kashish
Author-email: arpit@zinnov.com
License: UNKNOWN
Platform: UNKNOWN
Classifier: Framework :: Django
Classifier: Development Status :: 5 - Production/Stable
Classifier: Programming Language :: Python :: 3
Classifier: License :: OSI Approved :: MIT License
Classifier: Operating System :: OS Independent
